uP.v
//couenter principal para todo el procesador
module pcounter (input clk,
		 						input reset,
		 						input load,
		 						input enabled,
		 						input [11:0] d,
		 						output[11:0]PC);

wire clk, reset, load, enabled;
wire [11:0]d;
reg [11:0]PC;

always@(posedge clk, posedge reset) begin
	if (reset) begin
		PC<=0;
	end
	else if (load) begin
		PC<=d;
	end
	else if (enabled && !load) begin
		PC<=PC+1;
	end
	end
endmodule



//ROM
module memoria_ROM (input wire [11:0]addres, output wire [7:0]data);
	reg [7:0]mem[0:4095];

initial begin
	$readmemh("memoria.list",mem);
end

assign data = mem[addres];
endmodule



//f.f.D
module fetch(input clk, input reset,
	     input ena,
	     input [7:0]d,
	     output [3:0]instruccion,
	     output [3:0]operando);

	reg [3:0]instruccion;
	reg [3:0]operando;

	always @ (posedge clk, posedge reset)begin

		if (reset)
			begin
				operando <= 4'b0;
				instruccion <= 4'b0;
			end
		else if (ena)
			begin
				operando <= d[3:0];
				instruccion <= d[7:4];
			end
	end
endmodule
//f.f.D
module flag(input clk, input reset, input ena,
	     input carry, zero,
	     output reg c_flag,
			 output reg z_flag);

	always @ (posedge clk, posedge reset)begin
		if (reset)
			begin
				c_flag <= 1'b0;
				z_flag <= 1'b0;
			end
		else if (ena)
			begin
				c_flag <= carry;
				z_flag <= zero;
			end
	end
endmodule



//f.f.T
module phase(input clk, input reset, output logic q, output p);
	always @ (posedge clk, posedge reset)
		if (reset)
			q <= 0;
		else
			q <= ~q;
		assign p = ~q;
endmodule



// decode
module decode (input phase, input c_flag, input z_flag, input [3:0]instr,
							 output reg [12:0]comando);

	reg [6:0] in_decode;
	reg [12:0] out_decode;

		always @ ( * ) begin
		in_decode[0] <= phase;
		in_decode[1] <= z_flag;
		in_decode[2] <= c_flag;
		in_decode[6:3] <= instr;

		casez (in_decode)

			7'b??????0: out_decode <= 13'b1000000001000; //any
			7'b00001?1: out_decode <= 13'b0100000001000; //JC
			7'b00000?1: out_decode <= 13'b1000000001000; //JC
			7'b00011?1: out_decode <= 13'b1000000001000; //JNC
			7'b00010?1: out_decode <= 13'b0100000001000; //JNC
			7'b0010??1: out_decode <= 13'b0001001000010; //CMPI
			7'b0011??1: out_decode <= 13'b1001001100000; //CMPM
			7'b0100??1: out_decode <= 13'b0011010000010; //LIT
			7'b0101??1: out_decode <= 13'b0011010000100; //IN
			7'b0111??1: out_decode <= 13'b1000000111000; //LD
			7'b0110??1: out_decode <= 13'b1011010100000; //ST
			7'b1000?11: out_decode <= 13'b0100000001000; //JZ
			7'b1000?01: out_decode <= 13'b1000000001000; //JZ
			7'b1001?11: out_decode <= 13'b1000000001000; //JNZ
			7'b1001?01: out_decode <= 13'b0100000001000; //JNZ
			7'b1010??1: out_decode <= 13'b0011011000010; //ADDI
			7'b1011??1: out_decode <= 13'b1011011100000; //ADDM
			7'b1100??1: out_decode <= 13'b0100000001000; //JMP
			7'b1101??1: out_decode <= 13'b0000000001001; //OUT
			7'b1110??1: out_decode <= 13'b0011100000010; //NANDI
			7'b1111??1: out_decode <= 13'b1011100100000; //NANDM

			default: out_decode = 13'bxxxxxxxxxxxxx;

		endcase
		assign comando = out_decode;
	end
endmodule


module buftri(input ena, input [3:0] d, output [3:0] q);

    assign q = ena ? d : 4'bz;

endmodule



module accu(input clk, input reset, input ena, input [3:0]d, output logic [3:0]q);

	always @ (posedge clk, posedge reset)
		if (reset)
			q <= 4'b0;
		else if (ena)
			q <= d;
endmodule



module ALU(input [3:0] A, B,
           input [2:0] funcion,
           output carry, zero,
           output [3:0] resul);

    reg [4:0] regresul;

    always @ (A, B, funcion)
        case (funcion)
            3'b000: regresul = A;
            3'b001: regresul = A - B;
            3'b010: regresul = B;
            3'b011: regresul = A + B;
            3'b100: regresul = {1'b0, ~(A & B)};
            default: regresul = 5'b10101;
        endcase

    assign resul = regresul[3:0];
    assign carry = regresul[4];
    assign zero = ~(regresul[3] | regresul[2] | regresul[1] | regresul[0]);
endmodule


module RAM (input csRAM, weRAM,
            input [11:0] address,//in
            inout [3:0] data);

            reg [3:0] memory [0:4095]; //ram
            reg [3:0] data_out;


            always @ ( csRAM or weRAM or address or data) begin
              if ((csRAM == 1) && (weRAM == 1)) begin
                memory[address] <= data;
              end
              else if ((csRAM == 1) && (weRAM == 0)) begin
                data_out <= memory[address];
              end
            end

            assign data = (csRAM && !weRAM) ? data_out : 4'bzzzz;
endmodule

module addRam (input [7:0]program_byte, input [3:0]oprnd, output [11:0]address_RAM);
reg [11:0] address_RAM;

always @ ( * ) begin
	address_RAM [7:0] <= program_byte;
	address_RAM [11:8] <= oprnd;
end

endmodule // addRam


module uP (input clock, reset,
					 input [3:0] pushbuttons,
					 output phase, c_flag, z_flag,
					 output [3:0] instr,
					 output [3:0] oprnd,
					 output [3:0] data_bus,
					 output [3:0] FF_out,
					 output [3:0] accu,
					 output [7:0] program_byte,
					 output [11:0] PC,
					 output [11:0] address_RAM);

	wire clock, reset;
	wire carry, zero;
	wire phase, c_flag, z_flag, z_in, phaseN;
	wire [3:0]out_alu;
	wire [3:0]pushbuttons;
	wire [3:0] instr;
	wire [3:0] oprnd;
	wire [3:0] data_bus;
	wire [3:0] FF_out;
	wire [3:0] accu;
	wire [7:0] program_byte;
	wire [11:0] PC;
	wire [11:0] address_RAM;
	wire [12:0]comand;

	addRam addresram (.program_byte(program_byte), .oprnd(oprnd), .address_RAM(address_RAM) );

	pcounter prco(clock, reset, comand[11], comand[12], address_RAM, PC);

	memoria_ROM rom(.addres(PC), .data(program_byte) );

	fetch Fetch(.clk(clock), .reset(reset), .ena(phaseN), .d(program_byte), .instruccion(instr), .operando(oprnd) );

	phase p(.clk(clock), .reset(reset), .q(phase), .p(phaseN) );

	flag Flags(.clk(clock), .reset(reset), .ena(comand[9]), .carry(carry), .zero(zero), .c_flag(c_flag), .z_flag(z_flag) );

	decode Deco(.phase(phase), .c_flag(c_flag), .z_flag(z_flag), .instr(instr), .comando(comand) );

	buftri in_oprnd(.ena(comand[1]), .d(oprnd), .q(data_bus) );

	ALU alu(.A(accu), .B(data_bus), .funcion(comand[8:6]), .resul(out_alu), .carry(carry), .zero(zero) );

	accu acumu (.clk(clock), .reset(reset), .ena(comand[10]), .d(out_alu), .q(accu) );

	buftri OutALU(.ena(comand[3]), .d(out_alu), .q(data_bus) );

	RAM memram(.csRAM(comand[5]), .weRAM(comand[4]), .address(address_RAM), .data(data_bus) );

	buftri InPush(.ena(comand[2]), .d(pushbuttons), .q(data_bus) );

	buftri OutSi(.ena(comand[0]), .d(data_bus), .q(FF_out) );

endmodule

uP_tb.v
module testbench();

    reg clock, reset;
    reg [3:0] pushbuttons;
    wire phase, c_flag, z_flag;
    wire [3:0] instr, oprnd, accu, data_bus, FF_out;
    wire [7:0] program_byte;
    wire [11:0] PC, address_RAM;

    integer nota = 0;

    uP uPmodule(.clock(clock),
                .reset(reset),
                .pushbuttons(pushbuttons),
                .phase(phase),
                .c_flag(c_flag),
                .z_flag(z_flag),
                .instr(instr),
                .oprnd(oprnd),
                .accu(accu),
                .data_bus(data_bus),
                .FF_out(FF_out),
                .program_byte(program_byte),
                .PC(PC),
                .address_RAM(address_RAM));

    initial
        #500 $finish;

    always
        #5 clock = ~clock;

    initial begin
        clock = 0; reset = 0; pushbuttons = 4'b0110; nota = 0;
        #2 reset = 1;
        #1 reset = 0;
        $display("\n");
        $display("Bienvenido al testbench de su proyecto");
        $display("\n");
        $display("Para facilitar el código del testbench la nota se ha");
        $display("multplicado por 10. Es decir, la nota máxima de esta");
        $display("prueba es de 900. Obviamente su nota en Canvas no será de");
        $display("ese valor sino que se dividirá dentro de 10.");
        $display("Es decir, su nota es sobre 9.0 puntos netos.");
        $display("\n");
    end

    initial begin
        $dumpfile("uP_tb.vcd");
        $dumpvars(0, testbench);
    end

    initial begin
        #16
        if (PC === 12'h001 && accu === 4'h4) begin
            nota = nota + 70;
            $display("LIT funciona bien. Su nota es: %d/900\n", nota);
        end
        else
            $display("LIT NO funciona bien. Su nota es: %d/900\n", nota);
    end

    initial begin
        #36
        if (PC === 12'h002 && accu === 4'h4 && FF_out === 4'h4) begin
            nota = nota + 66;
            $display("OUT funciona bien. Su nota es: %d/900\n", nota);
        end
        else
            $display("OUT NO funciona bien. Su nota es: %d/900\n", nota);
    end

    initial begin
        #56
        if (PC === 12'h003 && accu === 4'h6 && FF_out === 4'h4) begin
            nota = nota + 66;
            $display("IN funciona bien. Su nota es: %d/900\n", nota);
        end
        else
            $display("IN NO funciona bien. Su nota es: %d/900\n", nota);
    end

    initial begin
        #76
        if (PC === 12'h004 && accu === 4'h0 && z_flag === 1'b1) begin
            $display("La bandera zero se encendió al colocar 4'b0000 en la salida de la ALU.\n");
        end
        else
            $display("La bandera zero NO se encendió al colocar 4'b0000 en la salida de la ALU.\n", nota);
    end

    initial begin
        #116
        if (PC === 12'h006 && accu === 4'h9 && c_flag === 1'b1) begin
            nota = nota + 33;
            $display("ADDI y la bandera carry funcionan bien. Su nota es: %d/900\n", nota);
        end
        else
            $display("ADDI y/o la bandera carry NO funcionan bien. Su nota es: %d/900\n", nota);
    end

    initial begin
        #136
        if (PC === 12'h007 && accu === 4'h9 && c_flag === 1'b0) begin
            nota = nota + 33;
            $display("CMPI de A > B hace que la bandera carry esté en 0 (como debería estar). Su nota es %d/900\n", nota);
        end
        else
            $display("CMPI de A > B causa que la bandera carry esté en 1 o modificó el valor del Accu. Su nota es %d/900\n", nota);
    end

    initial begin
        #176
        if (PC === 12'h009 && accu === 4'hA && c_flag === 1'b1) begin
            nota = nota + 33;
            $display("CMPI de A < B hace que la bandera carry esté en 1 (como debería estar). Su nota es %d/900\n", nota);
        end
        else
            $display("CMPI de A > B causa que la bandera carry esté en 1 o modificó el valor del Accu.  Su nota es %d/900\n", nota);
    end

    initial begin
        #196
        if (PC === 12'h00A && accu === 4'hB && c_flag === 1'b0 && z_flag === 1'b0) begin
            nota = nota + 33;
            $display("ADDI sin overflow no levanta las banderas (como debería estar). Su nota es %d/900\n", nota);
        end
        else
            $display("ADDI sin overflow levantó alguna de las banderas o no realizó bien la suma.  Su nota es %d/900\n", nota);
    end

    initial begin
        #216
        if (PC === 12'h00B && accu === 4'h4 && c_flag === 1'b0 && z_flag === 1'b0) begin
            nota = nota + 66;
            $display("NANDI funciona bien. Su nota es %d/900\n", nota);
        end
        else
            $display("NANDI NO funciona bien.  Su nota es %d/900\n", nota);
    end

    initial begin
        #276
        if (PC === 12'hA01) begin
            nota = nota + 60;
            $display("JMP funciona bien. Ahora estamos en PC = 12'hA01. Su nota es %d/900\n", nota);
        end
        else
            $display("JMP NO funciona bien. El PC no está en la localidad 12'HA01.  Su nota es %d/900\n", nota);
    end


endmodule

uP_tb.vcd
$date
	Wed Nov 18 20:45:33 2020
$end
$version
	Icarus Verilog
$end
$timescale
	1ps
$end
$scope module testbench $end
$var wire 4 ! data_bus [3:0] $end
$var wire 1 " z_flag $end
$var wire 8 # program_byte [7:0] $end
$var wire 1 $ phase $end
$var wire 4 % oprnd [3:0] $end
$var wire 4 & instr [3:0] $end
$var wire 1 ' c_flag $end
$var wire 12 ( address_RAM [11:0] $end
$var wire 4 ) accu [3:0] $end
$var wire 12 * PC [11:0] $end
$var wire 4 + FF_out [3:0] $end
$var reg 1 , clock $end
$var reg 4 - pushbuttons [3:0] $end
$var reg 1 . reset $end
$var integer 32 / nota [31:0] $end
$scope module uPmodule $end
$var wire 1 , clock $end
$var wire 4 0 data_bus [3:0] $end
$var wire 4 1 pushbuttons [3:0] $end
$var wire 1 . reset $end
$var wire 1 2 zero $end
$var wire 1 " z_flag $end
$var wire 8 3 program_byte [7:0] $end
$var wire 1 4 phaseN $end
$var wire 1 $ phase $end
$var wire 4 5 out_alu [3:0] $end
$var wire 4 6 oprnd [3:0] $end
$var wire 4 7 instr [3:0] $end
$var wire 13 8 comand [12:0] $end
$var wire 1 9 carry $end
$var wire 1 ' c_flag $end
$var wire 12 : address_RAM [11:0] $end
$var wire 4 ; accu [3:0] $end
$var wire 12 < PC [11:0] $end
$var wire 4 = FF_out [3:0] $end
$scope module Deco $end
$var wire 1 " z_flag $end
$var wire 1 $ phase $end
$var wire 4 > instr [3:0] $end
$var wire 1 ' c_flag $end
$var reg 13 ? comando [12:0] $end
$var reg 7 @ in_decode [6:0] $end
$var reg 13 A out_decode [12:0] $end
$upscope $end
$scope module Fetch $end
$var wire 1 , clk $end
$var wire 1 . reset $end
$var wire 1 4 ena $end
$var wire 8 B d [7:0] $end
$var reg 4 C instruccion [3:0] $end
$var reg 4 D operando [3:0] $end
$upscope $end
$scope module Flags $end
$var wire 1 , clk $end
$var wire 1 E ena $end
$var wire 1 . reset $end
$var wire 1 2 zero $end
$var wire 1 9 carry $end
$var reg 1 ' c_flag $end
$var reg 1 " z_flag $end
$upscope $end
$scope module InPush $end
$var wire 4 F d [3:0] $end
$var wire 1 G ena $end
$var wire 4 H q [3:0] $end
$upscope $end
$scope module OutALU $end
$var wire 1 I ena $end
$var wire 4 J q [3:0] $end
$var wire 4 K d [3:0] $end
$upscope $end
$scope module OutSi $end
$var wire 4 L d [3:0] $end
$var wire 1 M ena $end
$var wire 4 N q [3:0] $end
$upscope $end
$scope module acumu $end
$var wire 1 , clk $end
$var wire 1 O ena $end
$var wire 1 . reset $end
$var wire 4 P d [3:0] $end
$var reg 4 Q q [3:0] $end
$upscope $end
$scope module addresram $end
$var wire 4 R oprnd [3:0] $end
$var wire 8 S program_byte [7:0] $end
$var reg 12 T address_RAM [11:0] $end
$upscope $end
$scope module alu $end
$var wire 4 U A [3:0] $end
$var wire 4 V B [3:0] $end
$var wire 3 W funcion [2:0] $end
$var wire 1 2 zero $end
$var wire 4 X resul [3:0] $end
$var wire 1 9 carry $end
$var reg 5 Y regresul [4:0] $end
$upscope $end
$scope module in_oprnd $end
$var wire 4 Z d [3:0] $end
$var wire 1 [ ena $end
$var wire 4 \ q [3:0] $end
$upscope $end
$scope module memram $end
$var wire 12 ] address [11:0] $end
$var wire 1 ^ csRAM $end
$var wire 4 _ data [3:0] $end
$var wire 1 ` weRAM $end
$var reg 4 a data_out [3:0] $end
$upscope $end
$scope module p $end
$var wire 1 , clk $end
$var wire 1 4 p $end
$var wire 1 . reset $end
$var reg 1 $ q $end
$upscope $end
$scope module prco $end
$var wire 1 , clk $end
$var wire 12 b d [11:0] $end
$var wire 1 c enabled $end
$var wire 1 d load $end
$var wire 1 . reset $end
$var reg 12 e PC [11:0] $end
$upscope $end
$scope module rom $end
$var wire 12 f addres [11:0] $end
$var wire 8 g data [7:0] $end
$upscope $end
$upscope $end
$upscope $end
$enddefinitions $end
#0
$dumpvars
bx g
bx f
bx e
xd
xc
bx b
bx a
x`
bx _
x^
bx ]
bx \
x[
bx Z
bx Y
bx X
bx W
bx V
bx U
bx T
bx S
bx R
bx Q
bx P
xO
bx N
xM
bx L
bx K
bx J
xI
bx H
xG
b110 F
xE
bx D
bx C
bx B
bx A
bx @
bx ?
bx >
bx =
bx <
bx ;
bx :
x9
bx 8
bx 7
bx 6
bx 5
x4
bx 3
x2
b110 1
bx 0
b0 /
0.
b110 -
0,
bx +
bx *
bx )
bx (
x'
bx &
bx %
x$
bx #
x"
bx !
$end
#2
b0 !
b0 0
b0 H
b0 J
b0 L
b0 V
b0 \
b0 _
bz +
bz =
bz N
0M
0G
0`
0^
1I
0O
b0 W
0[
0E
1c
0d
b1000000001000 8
b1000000001000 ?
b1000000001000 A
b1000100 (
b1000100 :
b1000100 T
b1000100 ]
b1000100 b
b0 @
12
b0 5
b0 K
b0 P
b0 X
09
14
b0 Y
b1000100 #
b1000100 3
b1000100 B
b1000100 S
b1000100 g
b0 *
b0 <
b0 e
b0 f
b0 &
b0 7
b0 >
b0 C
b0 %
b0 6
b0 D
b0 R
b0 Z
0$
0"
0'
b0 )
b0 ;
b0 Q
b0 U
1.
#3
0.
#5
02
b100 5
b100 K
b100 P
b100 X
b100 Y
b100 !
b100 0
b100 H
b100 J
b100 L
b100 V
b100 \
b100 _
0I
1O
b10 W
1[
1E
0c
b11010000010 8
b11010000010 ?
b11010000010 A
b100001 @
b10011011111 (
b10011011111 :
b10011011111 T
b10011011111 ]
b10011011111 b
04
1$
b100 &
b100 7
b100 >
b100 C
b100 %
b100 6
b100 D
b100 R
b100 Z
b11011111 #
b11011111 3
b11011111 B
b11011111 S
b11011111 g
b1 *
b1 <
b1 e
b1 f
1,
#10
0,
#15
b100 !
b100 0
b100 H
b100 J
b100 L
b100 V
b100 \
b100 _
1I
0O
b0 W
0[
0E
1c
b1000000001000 8
b1000000001000 ?
b1000000001000 A
b100000 @
14
0$
b100 )
b100 ;
b100 Q
b100 U
1,
#16
b1000110 /
#20
0,
#25
b100 +
b100 =
b100 N
1M
0c
b1001 8
b1001 ?
b1001 A
b1101001 @
b111101010001 (
b111101010001 :
b111101010001 T
b111101010001 ]
b111101010001 b
04
1$
b1101 &
b1101 7
b1101 >
b1101 C
b1111 %
b1111 6
b1111 D
b1111 R
b1111 Z
b1010001 #
b1010001 3
b1010001 B
b1010001 S
b1010001 g
b10 *
b10 <
b10 e
b10 f
1,
#30
0,
#35
bz +
bz =
bz N
0M
1c
b1000000001000 8
b1000000001000 ?
b1000000001000 A
b1101000 @
14
0$
1,
#40
0,
#45
b110 5
b110 K
b110 P
b110 X
b110 Y
b110 !
b110 0
b110 H
b110 J
b110 L
b110 V
b110 \
b110 _
1G
0I
1O
b10 W
1E
0c
b11010000100 8
b11010000100 ?
b11010000100 A
b101001 @
b101000000 (
b101000000 :
b101000000 T
b101000000 ]
b101000000 b
04
1$
b101 &
b101 7
b101 >
b101 C
b1 %
b1 6
b1 D
b1 R
b1 Z
b1000000 #
b1000000 3
b1000000 B
b1000000 S
b1000000 g
b11 *
b11 <
b11 e
b11 f
1,
#50
0,
#55
0G
1I
0O
b0 W
0E
1c
b1000000001000 8
b1000000001000 ?
b1000000001000 A
b101000 @
14
0$
b110 )
b110 ;
b110 Q
b110 U
1,
#60
0,
#65
12
b0 5
b0 K
b0 P
b0 X
b0 Y
b0 !
b0 0
b0 H
b0 J
b0 L
b0 V
b0 \
b0 _
0I
1O
b10 W
1[
1E
0c
b11010000010 8
b11010000010 ?
b11010000010 A
b100001 @
b1001111 (
b1001111 :
b1001111 T
b1001111 ]
b1001111 b
04
1$
b100 &
b100 7
b100 >
b100 C
b0 %
b0 6
b0 D
b0 R
b0 Z
b1001111 #
b1001111 3
b1001111 B
b1001111 S
b1001111 g
b100 *
b100 <
b100 e
b100 f
1,
#70
0,
#75
b0 !
b0 0
b0 H
b0 J
b0 L
b0 V
b0 \
b0 _
1I
0O
b0 W
0[
0E
1c
b1000000001000 8
b1000000001000 ?
b1000000001000 A
b100010 @
14
0$
1"
b0 )
b0 ;
b0 Q
b0 U
1,
#80
0,
#85
02
b1111 5
b1111 K
b1111 P
b1111 X
b1111 Y
b1111 !
b1111 0
b1111 H
b1111 J
b1111 L
b1111 V
b1111 \
b1111 _
0I
1O
b10 W
1[
1E
0c
b11010000010 8
b11010000010 ?
b11010000010 A
b100011 @
b111110101010 (
b111110101010 :
b111110101010 T
b111110101010 ]
b111110101010 b
04
1$
b1111 %
b1111 6
b1111 D
b1111 R
b1111 Z
b10101010 #
b10101010 3
b10101010 B
b10101010 S
b10101010 g
b101 *
b101 <
b101 e
b101 f
1,
#90
0,
#95
b1111 !
b1111 0
b1111 H
b1111 J
b1111 L
b1111 V
b1111 \
b1111 _
1I
0O
b0 W
0[
0E
1c
b1000000001000 8
b1000000001000 ?
b1000000001000 A
b100000 @
14
0$
0"
b1111 )
b1111 ;
b1111 Q
b1111 U
1,
#100
0,
#105
b1001 5
b1001 K
b1001 P
b1001 X
19
b11001 Y
b1010 !
b1010 0
b1010 H
b1010 J
b1010 L
b1010 V
b1010 \
b1010 _
0I
1O
b11 W
1[
1E
0c
b11011000010 8
b11011000010 ?
b11011000010 A
b1010001 @
b101000101000 (
b101000101000 :
b101000101000 T
b101000101000 ]
b101000101000 b
04
1$
b1010 &
b1010 7
b1010 >
b1010 C
b1010 %
b1010 6
b1010 D
b1010 R
b1010 Z
b101000 #
b101000 3
b101000 B
b101000 S
b101000 g
b110 *
b110 <
b110 e
b110 f
1,
#110
0,
#115
09
b1001 !
b1001 0
b1001 H
b1001 J
b1001 L
b1001 V
b1001 \
b1001 _
1I
0O
b0 W
0[
0E
1c
b1000000001000 8
b1000000001000 ?
b1000000001000 A
b1010100 @
b1001 5
b1001 K
b1001 P
b1001 X
14
b1001 Y
0$
1'
b1001 )
b1001 ;
b1001 Q
b1001 U
1,
#116
b1100111 /
#120
0,
#125
b1 5
b1 K
b1 P
b1 X
09
b1 Y
b1000 !
b1000 0
b1000 H
b1000 J
b1000 L
b1000 V
b1000 \
b1000 _
0I
b1 W
1[
1E
0c
b1001000010 8
b1001000010 ?
b1001000010 A
b10101 @
b100001001010 (
b100001001010 :
b100001001010 T
b100001001010 ]
b100001001010 b
04
1$
b10 &
b10 7
b10 >
b10 C
b1000 %
b1000 6
b1000 D
b1000 R
b1000 Z
b1001010 #
b1001010 3
b1001010 B
b1001010 S
b1001010 g
b111 *
b111 <
b111 e
b111 f
1,
#130
0,
#135
b1001 5
b1001 K
b1001 P
b1001 X
b1001 Y
b1001 !
b1001 0
b1001 H
b1001 J
b1001 L
b1001 V
b1001 \
b1001 _
1I
b0 W
0[
0E
1c
b1000000001000 8
b1000000001000 ?
b1000000001000 A
b10000 @
14
0$
0'
1,
#136
b10001000 /
#140
0,
#145
b1010 5
b1010 K
b1010 P
b1010 X
b1010 Y
b1010 !
b1010 0
b1010 H
b1010 J
b1010 L
b1010 V
b1010 \
b1010 _
0I
1O
b10 W
1[
1E
0c
b11010000010 8
b11010000010 ?
b11010000010 A
b100001 @
b101000101100 (
b101000101100 :
b101000101100 T
b101000101100 ]
b101000101100 b
04
1$
b100 &
b100 7
b100 >
b100 C
b1010 %
b1010 6
b1010 D
b1010 R
b1010 Z
b101100 #
b101100 3
b101100 B
b101100 S
b101100 g
b1000 *
b1000 <
b1000 e
b1000 f
1,
#150
0,
#155
b1010 !
b1010 0
b1010 H
b1010 J
b1010 L
b1010 V
b1010 \
b1010 _
1I
0O
b0 W
0[
0E
1c
b1000000001000 8
b1000000001000 ?
b1000000001000 A
b100000 @
14
0$
b1010 )
b1010 ;
b1010 Q
b1010 U
1,
#160
0,
#165
b1110 5
b1110 K
b1110 P
b1110 X
19
b11110 Y
b1100 !
b1100 0
b1100 H
b1100 J
b1100 L
b1100 V
b1100 \
b1100 _
0I
b1 W
1[
1E
0c
b1001000010 8
b1001000010 ?
b1001000010 A
b10001 @
b110010100001 (
b110010100001 :
b110010100001 T
b110010100001 ]
b110010100001 b
04
1$
b10 &
b10 7
b10 >
b10 C
b1100 %
b1100 6
b1100 D
b1100 R
b1100 Z
b10100001 #
b10100001 3
b10100001 B
b10100001 S
b10100001 g
b1001 *
b1001 <
b1001 e
b1001 f
1,
#170
0,
#175
b1010 5
b1010 K
b1010 P
b1010 X
09
b1010 Y
b1010 !
b1010 0
b1010 H
b1010 J
b1010 L
b1010 V
b1010 \
b1010 _
1I
b0 W
0[
0E
1c
b1000000001000 8
b1000000001000 ?
b1000000001000 A
b10100 @
14
0$
1'
1,
#176
b10101001 /
#180
0,
#185
b1011 5
b1011 K
b1011 P
b1011 X
09
b1011 Y
b1 !
b1 0
b1 H
b1 J
b1 L
b1 V
b1 \
b1 _
0I
1O
b11 W
1[
1E
0c
b11011000010 8
b11011000010 ?
b11011000010 A
b1010101 @
b111101011 (
b111101011 :
b111101011 T
b111101011 ]
b111101011 b
04
1$
b1010 &
b1010 7
b1010 >
b1010 C
b1 %
b1 6
b1 D
b1 R
b1 Z
b11101011 #
b11101011 3
b11101011 B
b11101011 S
b11101011 g
b1010 *
b1010 <
b1010 e
b1010 f
1,
#190
0,
#195
b1011 !
b1011 0
b1011 H
b1011 J
b1011 L
b1011 V
b1011 \
b1011 _
1I
0O
b0 W
0[
0E
1c
b1000000001000 8
b1000000001000 ?
b1000000001000 A
b1010000 @
b1011 5
b1011 K
b1011 P
b1011 X
14
b1011 Y
0$
0'
b1011 )
b1011 ;
b1011 Q
b1011 U
1,
#196
b11001010 /
#200
0,
#205
b100 5
b100 K
b100 P
b100 X
b100 Y
0I
1O
b100 W
1[
1E
0c
b11100000010 8
b11100000010 ?
b11100000010 A
b1110001 @
b101111010000 (
b101111010000 :
b101111010000 T
b101111010000 ]
b101111010000 b
04
1$
b1110 &
b1110 7
b1110 >
b1110 C
b1011 %
b1011 6
b1011 D
b1011 R
b1011 Z
b11010000 #
b11010000 3
b11010000 B
b11010000 S
b11010000 g
b1011 *
b1011 <
b1011 e
b1011 f
1,
#210
0,
#215
b100 !
b100 0
b100 H
b100 J
b100 L
b100 V
b100 \
b100 _
1I
0O
b0 W
0[
0E
1c
b1000000001000 8
b1000000001000 ?
b1000000001000 A
b1110000 @
b100 5
b100 K
b100 P
b100 X
14
b100 Y
0$
b100 )
b100 ;
b100 Q
b100 U
1,
#216
b100001100 /
#220
0,
#225
b100 +
b100 =
b100 N
1M
0c
b1001 8
b1001 ?
b1001 A
b1101001 @
b1010000 (
b1010000 :
b1010000 T
b1010000 ]
b1010000 b
04
1$
b1101 &
b1101 7
b1101 >
b1101 C
b0 %
b0 6
b0 D
b0 R
b0 Z
b1010000 #
b1010000 3
b1010000 B
b1010000 S
b1010000 g
b1100 *
b1100 <
b1100 e
b1100 f
1,
#230
0,
#235
bz +
bz =
bz N
0M
1c
b1000000001000 8
b1000000001000 ?
b1000000001000 A
b1101000 @
14
0$
1,
#240
0,
#245
b110 5
b110 K
b110 P
b110 X
b110 Y
b110 !
b110 0
b110 H
b110 J
b110 L
b110 V
b110 \
b110 _
1G
0I
1O
b10 W
1E
0c
b11010000100 8
b11010000100 ?
b11010000100 A
b101001 @
b11001010 (
b11001010 :
b11001010 T
b11001010 ]
b11001010 b
04
1$
b101 &
b101 7
b101 >
b101 C
b11001010 #
b11001010 3
b11001010 B
b11001010 S
b11001010 g
b1101 *
b1101 <
b1101 e
b1101 f
1,
#250
0,
#255
0G
1I
0O
b0 W
0E
1c
b1000000001000 8
b1000000001000 ?
b1000000001000 A
b101000 @
14
0$
b110 )
b110 ;
b110 Q
b110 U
1,
#260
0,
#265
0c
1d
b100000001000 8
b100000001000 ?
b100000001000 A
b1100001 @
b101000000001 (
b101000000001 :
b101000000001 T
b101000000001 ]
b101000000001 b
04
1$
b1100 &
b1100 7
b1100 >
b1100 C
b1010 %
b1010 6
b1010 D
b1010 R
b1010 Z
b1 #
b1 3
b1 B
b1 S
b1 g
b1110 *
b1110 <
b1110 e
b1110 f
1,
#270
0,
#275
1c
0d
b1000000001000 8
b1000000001000 ?
b1000000001000 A
b101001000001 (
b101001000001 :
b101001000001 T
b101001000001 ]
b101001000001 b
b1100000 @
14
b1000001 #
b1000001 3
b1000001 B
b1000001 S
b1000001 g
b101000000001 *
b101000000001 <
b101000000001 e
b101000000001 f
0$
1,
#276
b101001000 /
#280
0,
#285
b1 5
b1 K
b1 P
b1 X
b1 Y
b1 !
b1 0
b1 H
b1 J
b1 L
b1 V
b1 \
b1 _
0I
1O
b10 W
1[
1E
0c
b11010000010 8
b11010000010 ?
b11010000010 A
b100001 @
b100100010 (
b100100010 :
b100100010 T
b100100010 ]
b100100010 b
04
1$
b100 &
b100 7
b100 >
b100 C
b1 %
b1 6
b1 D
b1 R
b1 Z
b100010 #
b100010 3
b100010 B
b100010 S
b100010 g
b101000000010 *
b101000000010 <
b101000000010 e
b101000000010 f
1,
#290
0,
#295
b1 !
b1 0
b1 H
b1 J
b1 L
b1 V
b1 \
b1 _
1I
0O
b0 W
0[
0E
1c
b1000000001000 8
b1000000001000 ?
b1000000001000 A
b100000 @
14
0$
b1 )
b1 ;
b1 Q
b1 U
1,
#300
0,
#305
02
b1111 5
b1111 K
b1111 P
b1111 X
19
b11111 Y
b10 !
b10 0
b10 H
b10 J
b10 L
b10 V
b10 \
b10 _
0I
b1 W
1[
1E
0c
b1001000010 8
b1001000010 ?
b1001000010 A
b10001 @
b1000000000 (
b1000000000 :
b1000000000 T
b1000000000 ]
b1000000000 b
04
1$
b10 &
b10 7
b10 >
b10 C
b10 %
b10 6
b10 D
b10 R
b10 Z
b0 #
b0 3
b0 B
b0 S
b0 g
b101000000011 *
b101000000011 <
b101000000011 e
b101000000011 f
1,
#310
0,
#315
b1 5
b1 K
b1 P
b1 X
09
b1 Y
b1 !
b1 0
b1 H
b1 J
b1 L
b1 V
b1 \
b1 _
1I
b0 W
0[
0E
1c
b1000000001000 8
b1000000001000 ?
b1000000001000 A
b10100 @
14
0$
1'
1,
#320
0,
#325
0c
1d
b100000001000 8
b100000001000 ?
b100000001000 A
b101 @
b1010000 (
b1010000 :
b1010000 T
b1010000 ]
b1010000 b
04
1$
b0 &
b0 7
b0 >
b0 C
b0 %
b0 6
b0 D
b0 R
b0 Z
b1010000 #
b1010000 3
b1010000 B
b1010000 S
b1010000 g
b101000000100 *
b101000000100 <
b101000000100 e
b101000000100 f
1,
#330
0,
#335
1c
0d
b1000000001000 8
b1000000001000 ?
b1000000001000 A
b1001111 (
b1001111 :
b1001111 T
b1001111 ]
b1001111 b
b100 @
14
b1001111 #
b1001111 3
b1001111 B
b1001111 S
b1001111 g
b1010000 *
b1010000 <
b1010000 e
b1010000 f
0$
1,
#340
0,
